Metadata-Version: 2.1
Name: packaging_demo-cjknobla
Version: 0.0.8
Summary: Demo packages for python course
Author-email: Chris Knoblauch <cjknobla@gmail.com>
License: MIT
Requires-Python: >=3.7
Requires-Dist: numpy
Requires-Dist: importlib-metadata; python_version < "3.10"
Provides-Extra: dev
Requires-Dist: packaging-demo-cjknobla[release,static-code-qa,test]; extra == "dev"
Provides-Extra: release
Requires-Dist: build; extra == "release"
Requires-Dist: twine; extra == "release"
Provides-Extra: static-code-qa
Requires-Dist: pre-commit; extra == "static-code-qa"
Provides-Extra: test
Requires-Dist: pytest; extra == "test"
Requires-Dist: pytest-cov; extra == "test"
